AUTHORS.md
CHANGELOG.md
LICENSE
MANIFEST.in
README.md
setup.cfg
setup.py
Uliweb.egg-info/PKG-INFO
Uliweb.egg-info/SOURCES.txt
Uliweb.egg-info/dependency_links.txt
Uliweb.egg-info/entry_points.txt
Uliweb.egg-info/not-zip-safe
Uliweb.egg-info/top_level.txt
test/test_app.py
test/test_cache.py
test/test_cache_obj.py
test/test_common.py
test/test_date.py
test/test_expose.py
test/test_form.py
test/test_generic.py
test/test_html.py
test/test_i18n.py
test/test_json.py
test/test_manage.py
test/test_multidb.py
test/test_orm.py
test/test_orm_ext.py
test/test_orm_extapp.py
test/test_pyini.py
test/test_secretkey.py
test/test_sorteddict.py
test/test_taglibs.py
test/test_template.py
test/test_url.py
test/test_workers.py
uliweb/.DS_Store
uliweb/__init__$py.class
uliweb/__init__.py
uliweb/__main__.py
uliweb/manage.py
uliweb/contrib/.DS_Store
uliweb/contrib/__init__.py
uliweb/contrib/auth/__init__.py
uliweb/contrib/auth/commands.py
uliweb/contrib/auth/config.ini
uliweb/contrib/auth/forms.py
uliweb/contrib/auth/info.ini
uliweb/contrib/auth/middle_auth.py
uliweb/contrib/auth/models.py
uliweb/contrib/auth/settings.ini
uliweb/contrib/auth/views.py
uliweb/contrib/auth/static/images/user20x20.jpg
uliweb/contrib/auth/static/images/user50x50.jpg
uliweb/contrib/auth/templates/login.html
uliweb/contrib/auth/templates/register.html
uliweb/contrib/cache/__init__.py
uliweb/contrib/cache/conf.py
uliweb/contrib/cache/info.ini
uliweb/contrib/cache/settings.ini
uliweb/contrib/celery/__init__.py
uliweb/contrib/celery/commands.py
uliweb/contrib/celery/settings.ini
uliweb/contrib/celery/tasks.py
uliweb/contrib/clean/.DS_Store
uliweb/contrib/clean/__init__.py
uliweb/contrib/clean/commands.py
uliweb/contrib/clean/subcommands.py
uliweb/contrib/clean/static/readme.txt
uliweb/contrib/clean/templates/readme.txt
uliweb/contrib/csrf/__init__.py
uliweb/contrib/csrf/conf.py
uliweb/contrib/csrf/config.ini
uliweb/contrib/csrf/info.ini
uliweb/contrib/csrf/middleware.py
uliweb/contrib/csrf/settings.ini
uliweb/contrib/csrf/static/readme.txt
uliweb/contrib/csrf/templates/inc_jquery_csrf.html
uliweb/contrib/csrf/templates/readme.txt
uliweb/contrib/datadict/__init__.py
