Metadata-Version: 1.1
Name: Uliweb
Version: 0.6
Summary: Easy python web framework
Home-page: https://github.com/limodou/uliweb
Author: limodou
Author-email: limodou@gmail.com
License: BSD
Keywords: wsgi web framework
Platform: any
Classifier: Development Status :: 5 - Production/Stable
Classifier: Environment :: Console
Classifier: Environment :: Web Environment
Classifier: Intended Audience :: Developers
Classifier: License :: OSI Approved :: BSD License
Classifier: Topic :: Internet :: WWW/HTTP :: WSGI
Classifier: Programming Language :: Python
Classifier: Operating System :: OS Independent
Classifier: Programming Language :: Python :: 2.6
Classifier: Programming Language :: Python :: 2.7
